LICENSE
MANIFEST.in
README.rst
setup.py
django_webfilemanager.egg-info/PKG-INFO
django_webfilemanager.egg-info/SOURCES.txt
django_webfilemanager.egg-info/dependency_links.txt
django_webfilemanager.egg-info/requires.txt
django_webfilemanager.egg-info/top_level.txt
filemanager/__init__.py
filemanager/admin.py
filemanager/core.py
filemanager/fields.py
filemanager/forms.py
filemanager/models.py
filemanager/settings.py
filemanager/signals.py
filemanager/urls.py
filemanager/utils.py
filemanager/views.py
filemanager/static/css/filemanager.css
filemanager/static/js/FileSaver.js
filemanager/static/js/checkbox.js
filemanager/static/js/filemanager.js
filemanager/static/js/jquery-2.1.0.min.js
filemanager/static/js/jquery.fileupload.js
filemanager/static/js/jquery.iframe-transport.js
filemanager/static/js/js-search.js
filemanager/static/js/jszip-utils.js
filemanager/static/js/jszip.js
filemanager/static/js/other.js
filemanager/static/js/zip_down.js
filemanager/static/js/vendor/jquery.ui.widget.js
filemanager/templates/filemanager/create_directory_modal.html
filemanager/templates/filemanager/file_info_modal.html
filemanager/templates/filemanager/filemanager_base.html
filemanager/templates/filemanager/filemanager_breadcrumbs.html
filemanager/templates/filemanager/filemanager_create_directory.html
filemanager/templates/filemanager/filemanager_field.html
filemanager/templates/filemanager/filemanager_upload.html
filemanager/templates/filemanager/remove_modal.html
filemanager/templates/filemanager/rename_modal.html
filemanager/templates/filemanager/upload_modal.html
filemanager/templates/filemanager/browser/filemanager_detail.html
filemanager/templates/filemanager/browser/filemanager_list.html
filemanager/tests/__init__.py
filemanager/tests/runtests.py
filemanager/tests/test.py
filemanager/tests/test_core.py