Metadata-Version: 1.1
Name: django-webfilemanager
Version: 1.1.0
Summary: Template for reusable django applications.
Home-page: https://github.com/rameezarshad/django-filemanager
Author: rameez
Author-email: rameez.arshad@outlook.in
License: BSD
Platform: UNKNOWN
Classifier: Development Status :: 1 - Planning
Classifier: Environment :: Web Environment
Classifier: Intended Audience :: Developers
Classifier: Framework :: Django
Classifier: License :: OSI Approved :: BSD License
Classifier: Operating System :: OS Independent
Classifier: Programming Language :: Python
